ant_upload_checker/__init__.py
ant_upload_checker/constants.py
ant_upload_checker/dupe_checker.py
ant_upload_checker/film_processor.py
ant_upload_checker/film_searcher.py
ant_upload_checker/main.py
ant_upload_checker/output.py
ant_upload_checker/setup_functions.py
ant_upload_checker/tests/test_dupe_checker.py
ant_upload_checker/tests/test_film_processor.py
ant_upload_checker/tests/test_film_searcher.py
ant_upload_checker/tests/test_setup_functions.py
ant_upload_checker-1.8.2.dist-info/licenses/LICENSE
ant_upload_checker-1.8.2.dist-info/METADATA
ant_upload_checker-1.8.2.dist-info/WHEEL
ant_upload_checker-1.8.2.dist-info/entry_points.txt
ant_upload_checker-1.8.2.dist-info/top_level.txt
ant_upload_checker-1.8.2.dist-info/RECORD
