Metadata-Version: 2.4
Name: ant_upload_checker
Version: 1.8.2
Summary: Check if local films have already been uploaded to ANT
Author: pizzaolive
License-Expression: MIT
Project-URL: Homepage, https://github.com/pizzaolive/ant_upload_checker
Project-URL: Issues, https://github.com/pizzaolive/ant_upload_checker/issues
Classifier: Programming Language :: Python :: 3
Classifier: Operating System :: OS Independent
Requires-Python: >=3.8
License-File: LICENSE
Requires-Dist: pandas>=2.0
Requires-Dist: requests>=2.0.0
Requires-Dist: ratelimit>=2.0.0
Requires-Dist: guessit>=3.8.0
Requires-Dist: inquirer>=3.3.0
Requires-Dist: python-dotenv>=1.0.1
Provides-Extra: test
Requires-Dist: pytest>7.0.0; extra == "test"
Dynamic: license-file
